{"nodes": [{"id": "packages_cost_optimizer_src_tracker_ts", "label": "tracker.ts", "file_type": "code", "source_file": "packages/cost-optimizer/src/tracker.ts", "source_location": "L1"}, {"id": "tracker_generatecostid", "label": "generateCostId()", "file_type": "code", "source_file": "packages/cost-optimizer/src/tracker.ts", "source_location": "L12"}, {"id": "tracker_createcostentry", "label": "createCostEntry()", "file_type": "code", "source_file": "packages/cost-optimizer/src/tracker.ts", "source_location": "L19"}, {"id": "tracker_getperiodboundaries", "label": "getPeriodBoundaries()", "file_type": "code", "source_file": "packages/cost-optimizer/src/tracker.ts", "source_location": "L34"}, {"id": "tracker_isinperiod", "label": "isInPeriod()", "file_type": "code", "source_file": "packages/cost-optimizer/src/tracker.ts", "source_location": "L75"}, {"id": "tracker_calculatesummary", "label": "calculateSummary()", "file_type": "code", "source_file": "packages/cost-optimizer/src/tracker.ts", "source_location": "L84"}, {"id": "tracker_gettotalcost", "label": "getTotalCost()", "file_type": "code", "source_file": "packages/cost-optimizer/src/tracker.ts", "source_location": "L119"}], "edges": [{"source": "packages_cost_optimizer_src_tracker_ts", "target": "packages_cost_optimizer_src_types_ts", "relation": "imports_from", "confidence": "EXTRACTED", "source_file": "packages/cost-optimizer/src/tracker.ts", "source_location": "L5", "weight": 1.0}, {"source": "packages_cost_optimizer_src_tracker_ts", "target": "tracker_generatecostid", "relation": "contains", "confidence": "EXTRACTED", "source_file": "packages/cost-optimizer/src/tracker.ts", "source_location": "L12", "weight": 1.0}, {"source": "packages_cost_optimizer_src_tracker_ts", "target": "tracker_createcostentry", "relation": "contains", "confidence": "EXTRACTED", "source_file": "packages/cost-optimizer/src/tracker.ts", "source_location": "L19", "weight": 1.0}, {"source": "packages_cost_optimizer_src_tracker_ts", "target": "tracker_getperiodboundaries", "relation": "contains", "confidence": "EXTRACTED", "source_file": "packages/cost-optimizer/src/tracker.ts", "source_location": "L34", "weight": 1.0}, {"source": "packages_cost_optimizer_src_tracker_ts", "target": "tracker_isinperiod", "relation": "contains", "confidence": "EXTRACTED", "source_file": "packages/cost-optimizer/src/tracker.ts", "source_location": "L75", "weight": 1.0}, {"source": "packages_cost_optimizer_src_tracker_ts", "target": "tracker_calculatesummary", "relation": "contains", "confidence": "EXTRACTED", "source_file": "packages/cost-optimizer/src/tracker.ts", "source_location": "L84", "weight": 1.0}, {"source": "packages_cost_optimizer_src_tracker_ts", "target": "tracker_gettotalcost", "relation": "contains", "confidence": "EXTRACTED", "source_file": "packages/cost-optimizer/src/tracker.ts", "source_location": "L119", "weight": 1.0}, {"source": "tracker_createcostentry", "target": "tracker_generatecostid", "relation": "calls", "confidence": "EXTRACTED", "source_file": "packages/cost-optimizer/src/tracker.ts", "source_location": "L26", "weight": 1.0}, {"source": "tracker_isinperiod", "target": "tracker_getperiodboundaries", "relation": "calls", "confidence": "EXTRACTED", "source_file": "packages/cost-optimizer/src/tracker.ts", "source_location": "L76", "weight": 1.0}, {"source": "tracker_gettotalcost", "target": "tracker_calculatesummary", "relation": "calls", "confidence": "EXTRACTED", "source_file": "packages/cost-optimizer/src/tracker.ts", "source_location": "L120", "weight": 1.0}], "raw_calls": [{"caller_nid": "tracker_generatecostid", "callee": "now", "source_file": "packages/cost-optimizer/src/tracker.ts", "source_location": "L13"}, {"caller_nid": "tracker_createcostentry", "callee": "toISOString", "source_file": "packages/cost-optimizer/src/tracker.ts", "source_location": "L27"}, {"caller_nid": "tracker_getperiodboundaries", "callee": "setHours", "source_file": "packages/cost-optimizer/src/tracker.ts", "source_location": "L44"}, {"caller_nid": "tracker_getperiodboundaries", "callee": "setDate", "source_file": "packages/cost-optimizer/src/tracker.ts", "source_location": "L50"}, {"caller_nid": "tracker_getperiodboundaries", "callee": "getDate", "source_file": "packages/cost-optimizer/src/tracker.ts", "source_location": "L50"}, {"caller_nid": "tracker_getperiodboundaries", "callee": "getDay", "source_file": "packages/cost-optimizer/src/tracker.ts", "source_location": "L50"}, {"caller_nid": "tracker_getperiodboundaries", "callee": "setHours", "source_file": "packages/cost-optimizer/src/tracker.ts", "source_location": "L51"}, {"caller_nid": "tracker_getperiodboundaries", "callee": "getFullYear", "source_file": "packages/cost-optimizer/src/tracker.ts", "source_location": "L56"}, {"caller_nid": "tracker_getperiodboundaries", "callee": "getMonth", "source_file": "packages/cost-optimizer/src/tracker.ts", "source_location": "L56"}, {"caller_nid": "tracker_calculatesummary", "callee": "filter", "source_file": "packages/cost-optimizer/src/tracker.ts", "source_location": "L88"}, {"caller_nid": "tracker_calculatesummary", "callee": "reduce", "source_file": "packages/cost-optimizer/src/tracker.ts", "source_location": "L90"}, {"caller_nid": "tracker_calculatesummary", "callee": "round", "source_file": "packages/cost-optimizer/src/tracker.ts", "source_location": "L107"}]}